vault_search/__init__.py
vault_search-0.2.11.dist-info/LICENSE
vault_search-0.2.11.dist-info/METADATA
vault_search-0.2.11.dist-info/WHEEL
vault_search-0.2.11.dist-info/entry_points.txt
vault_search-0.2.11.dist-info/top_level.txt
vault_search-0.2.11.dist-info/RECORD
