Metadata-Version: 2.1
Name: vault_search
Version: 0.2.11
Summary: Utility that searching inside vault
Home-page: https://gitlab.com/maksmikhalov/vault_search.git
Author: Maks Mikhalov
Author-email: dn2tx.com@gmail.com
Classifier: Programming Language :: Python :: 3
Classifier: License :: OSI Approved :: MIT License
Classifier: Operating System :: OS Independent
License-File: LICENSE
Requires-Dist: colorlog ~=6.8.2
Requires-Dist: requests ~=2.31.0
